{
  "contacts": [
    {
      "pseudo": "ghost-2306",
      "firstname": "Yannis",
      "lastname": "Bengueci",
      "email": "bengueci.yannis@gmail.com",
      "telephone": "+33614661834",
      "twitter": "lerealYaya",
      "facebook": "yannis bci",
      "id": 1
    },
    {
      "pseudo": "Clem94",
      "firstname": "Clement",
      "lastname": "Girnaud",
      "email": "clem.girnaud@mail.com",
      "telephone": "07070700",
      "twitter": "leClemOff",
      "facebook": "Clement Gir",
      "id": 2
    },
    {
      "pseudo": "gh0st_Fr",
      "firstname": "yzy",
      "lastname": "ddzz",
      "email": "dezdde@de",
      "telephone": "00000000",
      "twitter": "fefefe",
      "facebook": "fefezezez",
      "id": 3
    },
    {
      "pseudo": "i-rok",
      "firstname": "billy",
      "lastname": "guarik",
      "email": "b.guarik@mail.com",
      "telephone": "0606060606",
      "twitter": "lebillyG",
      "facebook": "b-guarik",
      "id": 4
    },
    {
      "pseudo": "eminem",
      "firstname": "Marshall",
      "lastname": "Matters",
      "email": "eminem@free.fr",
      "telephone": "0678986521",
      "twitter": "eminem_real",
      "facebook": "slimshady",
      "id": 5
    },
    {
      "pseudo": "TodMopel",
      "firstname": "Virgile",
      "lastname": "Benaitier",
      "email": "vbenaitier@mail.com",
      "telephone": "0654589231",
      "twitter": "leVirgileSauvage",
      "facebook": "v-benaitier",
      "id": 6
    },
    {
      "pseudo": "jb007",
      "firstname": "james",
      "lastname": "bond",
      "email": "jbond@mi6.com",
      "telephone": "007007007",
      "twitter": "jb007",
      "facebook": "james bond",
      "id": 7
    },
    {
      "pseudo": "leblob",
      "firstname": "jeremy",
      "lastname": "olipard",
      "email": "jolipard@mail.com",
      "telephone": "895623565",
      "twitter": "lolipard",
      "facebook": "olipard jeremy",
      "id": 9
    }
  ],
  "test": [
    {
      "gh0st_Fr": {
        "id": "user-1621968870846",
        "firstname": "clement",
        "lastname": "homavu",
        "email": "clem.homavu@mail.com",
        "telephone": "06060600",
        "twitter": "clemOf",
        "instagram": "leClem94"
      },
      "id": 1
    }
  ]
}